mcp_jira_python/__init__.py
mcp_jira_python/server.py
mcp_jira_python/tools/__init__.py
mcp_jira_python/tools/add_comment.py
mcp_jira_python/tools/add_comment_with_attachment.py
mcp_jira_python/tools/attach_content.py
mcp_jira_python/tools/attach_file.py
mcp_jira_python/tools/base.py
mcp_jira_python/tools/create_issue.py
mcp_jira_python/tools/create_issue_link.py
mcp_jira_python/tools/delete_issue.py
mcp_jira_python/tools/get_issue.py
mcp_jira_python/tools/get_issue_attachment.py
mcp_jira_python/tools/get_user.py
mcp_jira_python/tools/list_fields.py
mcp_jira_python/tools/list_issue_types.py
mcp_jira_python/tools/list_link_types.py
mcp_jira_python/tools/search_issues.py
mcp_jira_python/tools/update_issue.py
mseep_mcp_jira_python-0.1.1.dist-info/METADATA
mseep_mcp_jira_python-0.1.1.dist-info/WHEEL
mseep_mcp_jira_python-0.1.1.dist-info/entry_points.txt
mseep_mcp_jira_python-0.1.1.dist-info/licenses/LICENSE
mseep_mcp_jira_python-0.1.1.dist-info/RECORD
